{"statistics": [{"period": "ALL", "groups": [{"groupName": "Service", "statisticsItems": [{"name": "Aces", "home": "0", "away": "0", "compareCode": 3}, {"name": "Double faults", "home": "1", "away": "1", "compareCode": 3}, {"name": "First serve", "home": "40/53 (75%)", "away": "37/63 (59%)", "compareCode": 1}, {"name": "Second serve", "home": "12/13 (92%)", "away": "25/26 (96%)", "compareCode": 2}, {"name": "First serve points", "home": "23/40 (58%)", "away": "24/37 (65%)", "compareCode": 2}, {"name": "Second serve points", "home": "4/13 (31%)", "away": "12/26 (46%)", "compareCode": 2}, {"name": "Break points saved", "home": "2/6 (33%)", "away": "2/5 (40%)", "compareCode": 2}, {"name": "Service games played", "home": "8", "away": "9", "compareCode": 2}]}, {"groupName": "Return", "statisticsItems": [{"name": "First serve return points", "home": "13/37 (35%)", "away": "17/40 (42%)", "compareCode": 2}, {"name": "Second serve return points", "home": "14/26 (53%)", "away": "9/13 (69%)", "compareCode": 2}, {"name": "Break points converted", "home": "3", "away": "4", "compareCode": 2}, {"name": "Return games played", "home": "9", "away": "8", "compareCode": 2}]}, {"groupName": "Points", "statisticsItems": [{"name": "Service points won", "home": "27", "away": "36", "compareCode": 2}, {"name": "Receiver points won", "home": "27", "away": "26", "compareCode": 1}, {"name": "Total points won", "home": "54", "away": "62", "compareCode": 2}, {"name": "Max points in a row", "home": "8", "away": "6", "compareCode": 1}]}]}, {"period": "1ST", "groups": [{"groupName": "Service", "statisticsItems": [{"name": "Aces", "home": "0", "away": "0", "compareCode": 3}, {"name": "Double faults", "home": "1", "away": "1", "compareCode": 3}, {"name": "First serve", "home": "19/25 (76%)", "away": "16/30 (53%)", "compareCode": 1}, {"name": "Second serve", "home": "5/6 (83%)", "away": "13/14 (93%)", "compareCode": 2}, {"name": "First serve points", "home": "14/19 (74%)", "away": "10/16 (63%)", "compareCode": 1}, {"name": "Second serve points", "home": "3/6 (50%)", "away": "5/14 (36%)", "compareCode": 2}, {"name": "Break points saved", "home": "0/1 (0%)", "away": "2/4 (50%)", "compareCode": 1}, {"name": "Service games played", "home": "5", "away": "5", "compareCode": 3}]}, {"groupName": "Return", "statisticsItems": [{"name": "First serve return points", "home": "6/16 (37%)", "away": "5/19 (26%)", "compareCode": 2}, {"name": "Second serve return points", "home": "9/14 (64%)", "away": "3/6 (50%)", "compareCode": 2}, {"name": "Break points converted", "home": "2", "away": "1", "compareCode": 1}, {"name": "Return games played", "home": "5", "away": "5", "compareCode": 3}]}, {"groupName": "Points", "statisticsItems": [{"name": "Service points won", "home": "17", "away": "15", "compareCode": 1}, {"name": "Receiver points won", "home": "15", "away": "8", "compareCode": 1}, {"name": "Total points won", "home": "32", "away": "23", "compareCode": 1}, {"name": "Max points in a row", "home": "8", "away": "6", "compareCode": 1}]}]}, {"period": "2ND", "groups": [{"groupName": "Service", "statisticsItems": [{"name": "Aces", "home": "0", "away": "0", "compareCode": 3}, {"name": "Double faults", "home": "0", "away": "0", "compareCode": 3}, {"name": "First serve", "home": "13/19 (68%)", "away": "15/24 (63%)", "compareCode": 1}, {"name": "Second serve", "home": "6/6 (100%)", "away": "9/9 (100%)", "compareCode": 3}, {"name": "First serve points", "home": "4/13 (31%)", "away": "10/15 (67%)", "compareCode": 2}, {"name": "Second serve points", "home": "1/6 (17%)", "away": "5/9 (56%)", "compareCode": 2}, {"name": "Break points saved", "home": "2/5 (40%)", "away": "0/1 (0%)", "compareCode": 2}, {"name": "Service games played", "home": "3", "away": "4", "compareCode": 2}]}, {"groupName": "Return", "statisticsItems": [{"name": "First serve return points", "home": "5/15 (33%)", "away": "9/13 (69%)", "compareCode": 2}, {"name": "Second serve return points", "home": "4/9 (44%)", "away": "5/6 (83%)", "compareCode": 2}, {"name": "Break points converted", "home": "1", "away": "3", "compareCode": 2}, {"name": "Return games played", "home": "4", "away": "3", "compareCode": 2}]}, {"groupName": "Points", "statisticsItems": [{"name": "Service points won", "home": "5", "away": "15", "compareCode": 2}, {"name": "Receiver points won", "home": "9", "away": "14", "compareCode": 2}, {"name": "Total points won", "home": "14", "away": "29", "compareCode": 2}, {"name": "Max points in a row", "home": "3", "away": "6", "compareCode": 2}]}]}, {"period": "3RD", "groups": [{"groupName": "Service", "statisticsItems": [{"name": "Aces", "home": "0", "away": "0", "compareCode": 3}, {"name": "Double faults", "home": "0", "away": "0", "compareCode": 3}, {"name": "First serve", "home": "8/9 (89%)", "away": "6/9 (67%)", "compareCode": 1}, {"name": "Second serve", "home": "1/1 (100%)", "away": "3/3 (100%)", "compareCode": 3}, {"name": "First serve points", "home": "5/8 (63%)", "away": "4/6 (67%)", "compareCode": 1}, {"name": "Second serve points", "home": "0/1 (0%)", "away": "2/3 (67%)", "compareCode": 2}, {"name": "Break points saved", "home": "0/0 (0%)", "away": "0/0 (0%)", "compareCode": 3}, {"name": "Service games played", "home": "0", "away": "0", "compareCode": 3}]}, {"groupName": "Return", "statisticsItems": [{"name": "First serve return points", "home": "2/6 (33%)", "away": "3/8 (37%)", "compareCode": 3}, {"name": "Second serve return points", "home": "1/3 (33%)", "away": "1/1 (100%)", "compareCode": 2}, {"name": "Break points converted", "home": "0", "away": "0", "compareCode": 3}, {"name": "Return games played", "home": "0", "away": "0", "compareCode": 3}]}, {"groupName": "Points", "statisticsItems": [{"name": "Service points won", "home": "5", "away": "6", "compareCode": 2}, {"name": "Receiver points won", "home": "3", "away": "4", "compareCode": 2}, {"name": "Total points won", "home": "8", "away": "10", "compareCode": 2}, {"name": "Max points in a row", "home": "3", "away": "3", "compareCode": 3}]}]}]}